A3-4/4/alu_control.v
/*
member 1:
Name : Masthanaiah Chintamani
Roll : 191CS115
member 2:
Name : LSV Sandeep 
Roll : 191CS226

Date : 13th March,2021

module name : ALU CONTROL UNIT

*/

// alu  control module 
// this design  is taken from the riscv  book specified in the instruction
module control(func,op,operation);
input [1:0] op;
output [3:0] operation;
input [5:0] func;
wire w0;
not(w0,op[0]);
and(operation[3],w0,op[0]);
wire w1;
and(w1,op[1],func[1]);
or(operation[2],w1,op[0]);
wire w2,w3,w4;
not(w3,op[1]);
not(w4,func[2]);
or(operation[1],w3,w4);
or(w2,func[3],func[0]);
and(operation[0],op[1],w2);
endmodule

A2/2.ALU Control Design/alu_control/alu_control_tb.v
// test bench for the alu control 

module t();

reg [1:0] op;
wire [3:0] operation;
reg [5:0] func;

control c(func,op,operation);

initial begin
    $dumpfile("alu_control.vcd");
    $dumpvars(0,t);
    $monitor($time,". op:%b,funct:%b,operation:%b",op,func,operation);

    #5 op=2'b00;func=6'b000000; $display("ld,sd type");
    #5 op=2'b01;func=6'b000000; $display("branch type");
    #5 op=2'b10;func=6'b000000; $display("r-type  add");
    #5 op=2'b10;func=6'b000010; $display("r-type subtract");
    #5 op=2'b10;func=6'b000100; $display("r-type and");
    #5 op=2'b10;func=6'b000101; $display("r-type or");
    #5 op=2'b10;func=6'b001010; $display("r-type setless than");
end
endmodule

A2/2.ALU Control Design/alu_control/alu_control.vcd
$date
	Sun Mar 14 12:20:34 2021
$end
$version
	Icarus Verilog
$end
$timescale
	1s
$end
$scope module t $end
$var wire 4 ! operation [3:0] $end
$var reg 6 " func [5:0] $end
$var reg 2 # op [1:0] $end
$scope module c $end
$var wire 6 $ func [5:0] $end
$var wire 2 % op [1:0] $end
$var wire 1 & w0 $end
$var wire 1 ' w1 $end
$var wire 1 ( w2 $end
$var wire 1 ) w3 $end
$var wire 1 * w4 $end
$var wire 4 + operation [3:0] $end
$upscope $end
$upscope $end
$enddefinitions $end
#0
$dumpvars
bx +
x*
x)
x(
x'
x&
bx %
bx $
bx #
bx "
bx !
$end
#5
1*
0(
1&
0'
1)
b10 !
b10 +
b0 "
b0 $
b0 #
b0 %
#10
0&
b110 !
b110 +
b1 #
b1 %
#15
1&
b10 !
b10 +
0)
b10 #
b10 %
#20
b110 !
b110 +
1'
b10 "
b10 $
#25
b0 !
b0 +
0'
0*
b100 "
b100 $
#30
b1 !
b1 +
1(
b101 "
b101 $
#35
b111 !
b111 +
1'
1*
b1010 "
b1010 $
