A2/1.ALU Design/alu_bit/alu_bit.v
/*
member 1:
Name : Masthanaiah Chintamani
Roll : 191CS115
member 2:
Name : LSV Sandeep 
Roll : 191CS226

Date : 12th March,2021

Module Name : single bit alu design

*/


//mux 2:1 which take only one input and make 2 inputs internally one the input and other its inverse and depending on the control 
module mux(out,inp,c1);  //mux develop the a,invert of a with help of the control
output out;
input inp, c1;
wire n_inp;
not(n_inp,inp);
wire temp,temp1;
wire c1_not;
not(c1_not,c1);
and(temp,c1_not,inp);
and(temp1,c1,n_inp);
or(out,temp,temp1);
// assign out = (c1) ? ~inp:inp;
endmodule

// the following module is not used here as inputs are sent as one invert to another that is implemented as mux (above)
//this may be used further in next assignments
module mux_2inp(out,inp,inp1,c); //mux take 2 inputs and give one output with help of one control input
output out;
input inp,inp1,c;
wire c_inv;
not(c_inv,c);
wire and1,and2;
and(and1,c_inv,inp);
and(and2,c,inp1);
or(out,and1,and2);
endmodule

//takes the 4 inputs and with the help of additional two control inputs  generates the output 
// here c is  a 2-bit control input 
module mux_2(out,inp,inp1,inp2,inp3,c);//mux 4:1
output out;
input  inp,inp1,inp2,inp3;
input  [1:0] c ;
//assign out = (inp & ~c[0] & ~c[1]) | (inp1 & (c[0]) & ~(c[1])) |(inp2 & ~(c[0]) & (c[1])) | (inp3 & (c[0]) & (c[1]));

// following structural code can be replaced with above commented assign statement to get the desired output
wire w1,w2; 
not(w1,c[0]);
not(w2,c[1]);
wire choc,choc1,choc2,choc3;
and(choc,w1,w2);
and(choc1,c[0],w2);
and(choc2,w1,c[1]);
and(choc3,c[0],c[1]);
wire out1,out2,out3,out4;
and(out1,choc,inp);
and(out2,choc1,inp1);
and(out3,choc2,inp2);
and(out4,choc3,inp3);
wire dis,dis2;
or(dis,out1,out2);
or(dis1,out3,out4);
or(out,dis1,dis);
endmodule

//full adder module having the inputs a ,b, carry_in generates output carry_out and sum
module adder_full(cout,sum,a,b,cin); //full addder 
input a,b,cin;
output cout,sum;
wire w1;
xor(w1,a,b);
xor(sum,w1,cin);
//assign cout = a&b|a&cin|cin&b;
wire o1,o2;
and(o1,a,b);
and(o2,w1,cin);
or(cout,o1,o2);
endmodule
// single bit implementation taking the inputs a , b with help of carry in and left single bit inputs generating
// result of 64 -bit ,overflow flag ,zero check 
module alu_d(result,a,b,ain,bin,cin,c,cout,left); //1-bit alu 
input a,b,ain,bin,left,cin;
input [1:0] c;
output result,cout;
wire w1,w2,w3;
mux a1(w1,a,ain);
mux b1(w2,b,bin);
wire o,ad;
and(ad,w1,w2);
or(o,w1,w2);
adder_full q(cout,w3,a,w2,cin);
mux_2 m2(result,ad,o,w3,left,c);

endmodule

A2/1.ALU Design/alu_bit/alu_bit_tb.v
//test bench for the single bit alu


module tb();

reg a,b,ain,bin,left,cin;
reg [1:0] c;
wire result,cout;

alu_d z(result,a,b,ain,bin,cin,c,cout,left);

initial begin
    $dumpfile("alu_bit.vcd");
    $dumpvars(0,tb);

$monitor($time,".result: %b, a:%b, b:%b, a_inv:%b, b_inv:%b, carry_in:%b, left:%b, carry_out:%b,control :%b",result,a,b,ain,bin,cin,left,cout,c);

        #5  $display("or gate  "); a=1;b=0;ain=0;bin=0;c=1;  // or gate
           #5  $display("and gate  "); a=1;b=0;ain=0;bin=0;c=0;   //and gate
           #5  $display("nand gate  "); a=0;b=1;ain=1;bin=1;c=0;   // nand gate
           #5  $display("nor gate  "); a=0;b=0;ain=1;bin=1;c=1;   //nor gate
           #5  $display("subtration  "); a=0;b=1;ain=0;bin=1;c=2; cin=1;  //sub
           #5  $display("sum  "); a=1;b=1;ain=0;bin=0;c=2;   cin=0;        //sum
           #5  $display("zero check  "); a=0;b=0;ain=0;bin=0;c=2;     //zero
           #5  $display("slt check  "); a=0;b=1;ain=0;bin=1;c=3;cin=1;left=0;   //slt it is useful in 64-bit alu 
		#5  $display("slt check  "); a=0;b=1;ain=0;bin=1;c=3;cin=1;left=1;	
	   #10 $finish;
   end

endmodule

A2/1.ALU Design/alu_bit/alu_bit.vcd
$date
	Sun Mar 14 11:13:42 2021
$end
$version
	Icarus Verilog
$end
$timescale
	1s
$end
$scope module tb $end
$var wire 1 ! result $end
$var wire 1 " cout $end
$var reg 1 # a $end
$var reg 1 $ ain $end
$var reg 1 % b $end
$var reg 1 & bin $end
$var reg 2 ' c [1:0] $end
$var reg 1 ( cin $end
$var reg 1 ) left $end
$scope module z $end
$var wire 1 # a $end
$var wire 1 * ad $end
$var wire 1 $ ain $end
$var wire 1 % b $end
$var wire 1 & bin $end
$var wire 2 + c [1:0] $end
$var wire 1 ( cin $end
$var wire 1 ) left $end
$var wire 1 , o $end
$var wire 1 - w3 $end
$var wire 1 . w2 $end
$var wire 1 / w1 $end
$var wire 1 ! result $end
$var wire 1 " cout $end
$scope module a1 $end
$var wire 1 $ c1 $end
$var wire 1 0 c1_not $end
$var wire 1 # inp $end
$var wire 1 1 n_inp $end
$var wire 1 / out $end
$var wire 1 2 temp $end
$var wire 1 3 temp1 $end
$upscope $end
$scope module b1 $end
$var wire 1 & c1 $end
$var wire 1 4 c1_not $end
$var wire 1 % inp $end
$var wire 1 5 n_inp $end
$var wire 1 . out $end
$var wire 1 6 temp $end
$var wire 1 7 temp1 $end
$upscope $end
$scope module m2 $end
$var wire 2 8 c [1:0] $end
$var wire 1 9 choc $end
$var wire 1 : choc1 $end
$var wire 1 ; choc2 $end
$var wire 1 < choc3 $end
$var wire 1 = dis $end
$var wire 1 > dis1 $end
$var wire 1 * inp $end
$var wire 1 , inp1 $end
$var wire 1 ) inp3 $end
$var wire 1 ! out $end
$var wire 1 ? out1 $end
$var wire 1 @ out2 $end
$var wire 1 A out3 $end
$var wire 1 B out4 $end
$var wire 1 C w1 $end
$var wire 1 D w2 $end
$var wire 1 - inp2 $end
$upscope $end
$scope module q $end
$var wire 1 # a $end
$var wire 1 . b $end
$var wire 1 ( cin $end
$var wire 1 " cout $end
$var wire 1 E o1 $end
$var wire 1 F o2 $end
$var wire 1 - sum $end
$var wire 1 G w1 $end
$upscope $end
$upscope $end
$upscope $end
$enddefinitions $end
#0
$dumpvars
xG
xF
xE
xD
xC
xB
xA
x@
x?
x>
x=
x<
x;
x:
x9
bx 8
x7
x6
x5
x4
x3
x2
x1
x0
x/
x.
x-
x,
bx +
x*
x)
x(
bx '
x&
x%
x$
x#
x"
x!
$end
#5
1!
1=
1@
0>
1,
0?
09
1:
0A
0B
1/
1G
0E
0*
0C
1D
0;
0<
12
0.
14
07
10
03
15
06
01
b1 '
b1 +
b1 8
0&
0$
0%
1#
#10
0!
0=
19
0@
1C
0:
b0 '
b0 +
b0 8
#15
0!
0=
0?
0*
0"
0.
0F
04
00
13
05
06
11
02
0G
1&
1$
1%
0#
#20
x"
1!
xF
1=
1G
1*
09
1@
1.
0C
1:
17
15
b1 '
b1 +
b1 8
0%
#25
1>
1A
1!
0=
0G
1;
0@
0,
0*
0.
0"
1C
0D
0:
0/
07
1-
0F
10
03
05
1(
b10 '
b10 +
b10 8
0$
1%
#30
0!
0>
0A
0-
1"
1E
1*
1.
1,
16
1/
14
01
12
0G
0(
0&
1#
#35
0!
0>
0,
0*
0A
0.
0/
0-
0"
15
06
11
02
0G
0E
0%
0#
#40
0"
0!
0F
0>
0;
0G
0,
0A
0C
1<
0.
1-
04
05
06
0)
1(
b11 '
b11 +
b11 8
1&
1%
#45
1!
1>
1B
1)
